aiscout/__init__.py
aiscout/scout.py
aiscout/modules/__init__.py
aiscout/modules/bbox.py
aiscout/modules/box_utils.py
aiscout/modules/color_analysis.py
aiscout/modules/debug_output.py
aiscout/modules/image_utils.py
aiscout/modules/visualization.py
aiscout/prompts/__init__.py
aiscout/prompts/analyze_targets.py
aiscout/prompts/identify_objects.py
aiscout/prompts/manager.py
aiscout/prompts/refine_detections.py
aiscout/providers/__init__.py
aiscout/providers/anthropic.py
aiscout/providers/base.py
aiscout/providers/openai.py
aiscout-0.1.0.dist-info/LICENSE
aiscout-0.1.0.dist-info/METADATA
aiscout-0.1.0.dist-info/WHEEL
aiscout-0.1.0.dist-info/top_level.txt
aiscout-0.1.0.dist-info/RECORD
