Metadata-Version: 2.2
Name: aiscout
Version: 0.1.0
Summary: A lightning fast and insanely accurate agentic object detection system
Author-email: Jacob Weiss <jaweiss2305@gmail.com>
Requires-Python: >=3.9
License-File: LICENSE
Requires-Dist: ultralytics
Requires-Dist: requests
Requires-Dist: rich
